{"cod":"200","message":0,"cnt":40,"list":[{"dt":1615064400,"main":{"temp":62.19,"feels_like":60.53,"temp_min":59.79,"temp_max":62.19,"pressure":1015,"sea_level":1015,"grnd_level":717,"humidity":62,"temp_kf":1.33},"weather":[{"id":500,"main":"Rain","description":"light rain","icon":"10d"}],"clouds":{"all":83},"wind":{"speed":2.62,"deg":328},"visibility":1417,"pop":0.97,"rain":{"3h":2.76},"sys":{"pod":"d"},"dt_txt":"2021-03-06 21:00:00"},{"dt":1615075200,"main":{"temp":55.8,"feels_like":55.06,"temp_min":53.42,"temp_max":55.8,"pressure":1014,"sea_level":1014,"grnd_level":716,"humidity":78,"temp_kf":1.32},"weather":[{"id":501,"main":"Rain","description":"moderate rain","icon":"10n"}],"clouds":{"all":88},"wind":{"speed":1.01,"deg":344},"visibility":819,"pop":0.98,"rain":{"3h":3.42},"sys":{"pod":"n"},"dt_txt":"2021-03-07 00:00:00"},{"dt":1615086000,"main":{"temp":51.98,"feels_like":49.39,"temp_min":51.13,"temp_max":51.98,"pressure":1015,"sea_level":1015,"grnd_level":717,"humidity":81,"temp_kf":0.47},"weather":[{"id":500,"main":"Rain","description":"light rain","icon":"10n"}],"clouds":{"all":74},"wind":{"speed":3.09,"deg":106},"visibility":10000,"pop":0.76,"rain":{"3h":1.96},"sys":{"pod":"n"},"dt_txt":"2021-03-07 03:00:00"},{"dt":1615096800,"main":{"temp":49.57,"feels_like":46.72,"temp_min":49.44,"temp_max":49.57,"pressure":1014,"sea_level":1014,"grnd_level":716,"humidity":81,"temp_kf":0.07},"weather":[{"id":500,"main":"Rain","description":"light rain","icon":"10n"}],"clouds":{"all":71},"wind":{"speed":2.57,"deg":126},"visibility":10000,"pop":0.7,"rain":{"3h":0.28},"sys":{"pod":"n"},"dt_txt":"2021-03-07 06:00:00"},{"dt":1615107600,"main":{"temp":48.42,"feels_like":45.32,"temp_min":48.42,"temp_max":48.42,"pressure":1013,"sea_level":1013,"grnd_level":714,"humidity":82,"temp_kf":0},"weather":[{"id":804,"main":"Clouds","description":"overcast clouds","icon":"04n"}],"clouds":{"all":91},"wind":{"speed":2.71,"deg":118},"visibility":10000,"pop":0.56,"sys":{"pod":"n"},"dt_txt":"2021-03-07 09:00:00"},{"dt":1615118400,"main":{"temp":49.35,"feels_like":46.42,"temp_min":49.35,"temp_max":49.35,"pressure":1015,"sea_level":1015,"grnd_level":716,"humidity":80,"temp_kf":0},"weather":[{"id":500,"main":"Rain","description":"light rain","icon":"10d"}],"clouds":{"all":95},"wind":{"speed":2.53,"deg":135},"visibility":10000,"pop":0.44,"rain":{"3h":0.14},"sys":{"pod":"d"},"dt_txt":"2021-03-07 12:00:00"},{"dt":1615129200,"main":{"temp":61.5,"feels_like":59.54,"temp_min":61.5,"temp_max":61.5,"pressure":1016,"sea_level":1016,"grnd_level":723,"humidity":60,"temp_kf":0},"weather":[{"id":500,"main":"Rain","description":"light rain","icon":"10d"}],"clouds":{"all":61},"wind":{"speed":2.46,"deg":3},"visibility":10000,"pop":0.54,"rain":{"3h":0.23},"sys":{"pod":"d"},"dt_txt":"2021-03-07 15:00:00"},{"dt":1615140000,"main":{"temp":58.5,"feels_like":56.19,"temp_min":58.5,"temp_max":58.5,"pressure":1014,"sea_level":1014,"grnd_level":719,"humidity":70,"temp_kf":0},"weather":[{"id":500,"main":"Rain","description":"light rain","icon":"10d"}],"clouds":{"all":66},"wind":{"speed":3.65,"deg":345},"visibility":1096,"pop":0.98,"rain":{"3h":2.34},"sys":{"pod":"d"},"dt_txt":"2021-03-07 18:00:00"},{"dt":1615150800,"main":{"temp":54.59,"feels_like":52.7,"temp_min":54.59,"temp_max":54.59,"pressure":1012,"sea_level":1012,"grnd_level":716,"humidity":82,"temp_kf":0},"weather":[{"id":501,"main":"Rain","description":"moderate rain","icon":"10d"}],"clouds":{"all":100},"wind":{"speed":3.11,"deg":359},"visibility":1348,"pop":1,"rain":{"3h":5.29},"sys":{"pod":"d"},"dt_txt":"2021-03-07 21:00:00"},{"dt":1615161600,"main":{"temp":52.7,"feels_like":50.58,"temp_min":52.7,"temp_max":52.7,"pressure":1014,"sea_level":1014,"grnd_level":717,"humidity":81,"temp_kf":0},"weather":[{"id":501,"main":"Rain","description":"moderate rain","icon":"10n"}],"clouds":{"all":100},"wind":{"speed":2.55,"deg":100},"visibility":10000,"pop":1,"rain":{"3h":3.49},"sys":{"pod":"n"},"dt_txt":"2021-03-08 00:00:00"},{"dt":1615172400,"main":{"temp":51.46,"feels_like":49.37,"temp_min":51.46,"temp_max":51.46,"pressure":1016,"sea_level":1016,"grnd_level":718,"humidity":83,"temp_kf":0},"weather":[{"id":500,"main":"Rain","description":"light rain","icon":"10n"}],"clouds":{"all":100},"wind":{"speed":2.24,"deg":96},"visibility":10000,"pop":0.91,"rain":{"3h":0.62},"sys":{"pod":"n"},"dt_txt":"2021-03-08 03:00:00"},{"dt":1615183200,"main":{"temp":50.52,"feels_like":49.24,"temp_min":50.52,"temp_max":50.52,"pressure":1016,"sea_level":1016,"grnd_level":717,"humidity":83,"temp_kf":0},"weather":[{"id":500,"main":"Rain","description":"light rain","icon":"10n"}],"clouds":{"all":100},"wind":{"speed":0.43,"deg":200},"visibility":10000,"pop":0.7,"rain":{"3h":0.22},"sys":{"pod":"n"},"dt_txt":"2021-03-08 06:00:00"},{"dt":1615194000,"main":{"temp":50.29,"feels_like":49.17,"temp_min":50.29,"temp_max":50.29,"pressure":1014,"sea_level":1014,"grnd_level":716,"humidity":86,"temp_kf":0},"weather":[{"id":500,"main":"Rain","description":"light rain","icon":"10n"}],"clouds":{"all":100},"wind":{"speed":0.43,"deg":98},"visibility":10000,"pop":0.43,"rain":{"3h":0.2},"sys":{"pod":"n"},"dt_txt":"2021-03-08 09:00:00"},{"dt":1615204800,"main":{"temp":49.53,"feels_like":47.93,"temp_min":49.53,"temp_max":49.53,"pressure":1016,"sea_level":1016,"grnd_level":717,"humidity":86,"temp_kf":0},"weather":[{"id":804,"main":"Clouds","description":"overcast clouds","icon":"04d"}],"clouds":{"all":100},"wind":{"speed":0.98,"deg":129},"visibility":10000,"pop":0.34,"sys":{"pod":"d"},"dt_txt":"2021-03-08 12:00:00"},{"dt":1615215600,"main":{"temp":59.32,"feels_like":56.88,"temp_min":59.32,"temp_max":59.32,"pressure":1017,"sea_level":1017,"grnd_level":722,"humidity":68,"temp_kf":0},"weather":[{"id":500,"main":"Rain","description":"light rain","icon":"10d"}],"clouds":{"all":70},"wind":{"speed":3.91,"deg":324},"visibility":6778,"pop":0.5,"rain":{"3h":0.39},"sys":{"pod":"d"},"dt_txt":"2021-03-08 15:00:00"},{"dt":1615226400,"main":{"temp":55.53,"feels_like":53.02,"temp_min":55.53,"temp_max":55.53,"pressure":1015,"sea_level":1015,"grnd_level":719,"humidity":80,"temp_kf":0},"weather":[{"id":500,"main":"Rain","description":"light rain","icon":"10d"}],"clouds":{"all":79},"wind":{"speed":4.34,"deg":323},"visibility":662,"pop":1,"rain":{"3h":2.86},"sys":{"pod":"d"},"dt_txt":"2021-03-08 18:00:00"},{"dt":1615237200,"main":{"temp":51.73,"feels_like":50.09,"temp_min":51.73,"temp_max":51.73,"pressure":1013,"sea_level":1013,"grnd_level":716,"humidity":86,"temp_kf":0},"weather":[{"id":501,"main":"Rain","description":"moderate rain","icon":"10d"}],"clouds":{"all":100},"wind":{"speed":1.99,"deg":243},"visibility":3130,"pop":1,"rain":{"3h":10.01},"sys":{"pod":"d"},"dt_txt":"2021-03-08 21:00:00"},{"dt":1615248000,"main":{"temp":50.9,"feels_like":48.97,"temp_min":50.9,"temp_max":50.9,"pressure":1015,"sea_level":1015,"grnd_level":717,"humidity":84,"temp_kf":0},"weather":[{"id":501,"main":"Rain","description":"moderate rain","icon":"10n"}],"clouds":{"all":100},"wind":{"speed":1.88,"deg":245},"visibility":10000,"pop":1,"rain":{"3h":3.5},"sys":{"pod":"n"},"dt_txt":"2021-03-09 00:00:00"},{"dt":1615258800,"main":{"temp":50.74,"feels_like":49.64,"temp_min":50.74,"temp_max":50.74,"pressure":1017,"sea_level":1017,"grnd_level":718,"humidity":86,"temp_kf":0},"weather":[{"id":500,"main":"Rain","description":"light rain","icon":"10n"}],"clouds":{"all":100},"wind":{"speed":0.6,"deg":320},"visibility":2909,"pop":0.75,"rain":{"3h":1.57},"sys":{"pod":"n"},"dt_txt":"2021-03-09 03:00:00"},{"dt":1615269600,"main":{"temp":50.05,"feels_like":48.83,"temp_min":50.05,"temp_max":50.05,"pressure":1015,"sea_level":1015,"grnd_level":717,"humidity":88,"temp_kf":0},"weather":[{"id":500,"main":"Rain","description":"light rain","icon":"10n"}],"clouds":{"all":100},"wind":{"speed":0.78,"deg":1},"visibility":2174,"pop":1,"rain":{"3h":0.95},"sys":{"pod":"n"},"dt_txt":"2021-03-09 06:00:00"},{"dt":1615280400,"main":{"temp":49.64,"feels_like":48.33,"temp_min":49.64,"temp_max":49.64,"pressure":1013,"sea_level":1013,"grnd_level":715,"humidity":88,"temp_kf":0},"weather":[{"id":500,"main":"Rain","description":"light rain","icon":"10n"}],"clouds":{"all":100},"wind":{"speed":0.76,"deg":7},"visibility":2968,"pop":1,"rain":{"3h":1.65},"sys":{"pod":"n"},"dt_txt":"2021-03-09 09:00:00"},{"dt":1615291200,"main":{"temp":50.11,"feels_like":48.81,"temp_min":50.11,"temp_max":50.11,"pressure":1015,"sea_level":1015,"grnd_level":716,"humidity":88,"temp_kf":0},"weather":[{"id":500,"main":"Rain","description":"light rain","icon":"10d"}],"clouds":{"all":100},"wind":{"speed":0.94,"deg":18},"visibility":7301,"pop":0.99,"rain":{"3h":1.33},"sys":{"pod":"d"},"dt_txt":"2021-03-09 12:00:00"},{"dt":1615302000,"main":{"temp":54.03,"feels_like":52.86,"temp_min":54.03,"temp_max":54.03,"pressure":1016,"sea_level":1016,"grnd_level":719,"humidity":78,"temp_kf":0},"weather":[{"id":500,"main":"Rain","description":"light rain","icon":"10d"}],"clouds":{"all":100},"wind":{"speed":1.01,"deg":278},"visibility":10000,"pop":0.72,"rain":{"3h":0.89},"sys":{"pod":"d"},"dt_txt":"2021-03-09 15:00:00"},{"dt":1615312800,"main":{"temp":55.44,"feels_like":53.37,"temp_min":55.44,"temp_max":55.44,"pressure":1014,"sea_level":1014,"grnd_level":718,"humidity":77,"temp_kf":0},"weather":[{"id":500,"main":"Rain","description":"light rain","icon":"10d"}],"clouds":{"all":97},"wind":{"speed":3.04,"deg":298},"visibility":5652,"pop":0.96,"rain":{"3h":1.53},"sys":{"pod":"d"},"dt_txt":"2021-03-09 18:00:00"},{"dt":1615323600,"main":{"temp":53.47,"feels_like":51.58,"temp_min":53.47,"temp_max":53.47,"pressure":1011,"sea_level":1011,"grnd_level":715,"humidity":82,"temp_kf":0},"weather":[{"id":500,"main":"Rain","description":"light rain","icon":"10d"}],"clouds":{"all":99},"wind":{"speed":2.62,"deg":303},"visibility":4110,"pop":0.92,"rain":{"3h":1.69},"sys":{"pod":"d"},"dt_txt":"2021-03-09 21:00:00"},{"dt":1615334400,"main":{"temp":51.48,"feels_like":49.77,"temp_min":51.48,"temp_max":51.48,"pressure":1013,"sea_level":1013,"grnd_level":716,"humidity":89,"temp_kf":0},"weather":[{"id":500,"main":"Rain","description":"light rain","icon":"10n"}],"clouds":{"all":100},"wind":{"speed":2.39,"deg":339},"visibility":591,"pop":0.93,"rain":{"3h":2.09},"sys":{"pod":"n"},"dt_txt":"2021-03-10 00:00:00"},{"dt":1615345200,"main":{"temp":49.87,"feels_like":48.51,"temp_min":49.87,"temp_max":49.87,"pressure":1016,"sea_level":1016,"grnd_level":717,"humidity":91,"temp_kf":0},"weather":[{"id":501,"main":"Rain","description":"moderate rain","icon":"10n"}],"clouds":{"all":100},"wind":{"speed":1.34,"deg":298},"visibility":2143,"pop":0.95,"rain":{"3h":6.77},"sys":{"pod":"n"},"dt_txt":"2021-03-10 03:00:00"},{"dt":1615356000,"main":{"temp":48.72,"feels_like":46.08,"temp_min":48.72,"temp_max":48.72,"pressure":1015,"sea_level":1015,"grnd_level":716,"humidity":88,"temp_kf":0},"weather":[{"id":501,"main":"Rain","description":"moderate rain","icon":"10n"}],"clouds":{"all":100},"wind":{"speed":2.77,"deg":115},"visibility":7842,"pop":0.98,"rain":{"3h":6.55},"sys":{"pod":"n"},"dt_txt":"2021-03-10 06:00:00"},{"dt":1615366800,"main":{"temp":48.67,"feels_like":46.17,"temp_min":48.67,"temp_max":48.67,"pressure":1013,"sea_level":1013,"grnd_level":714,"humidity":85,"temp_kf":0},"weather":[{"id":500,"main":"Rain","description":"light rain","icon":"10n"}],"clouds":{"all":100},"wind":{"speed":2.1,"deg":169},"visibility":10000,"pop":0.73,"rain":{"3h":2.56},"sys":{"pod":"n"},"dt_txt":"2021-03-10 09:00:00"},{"dt":1615377600,"main":{"temp":49.73,"feels_like":47.5,"temp_min":49.73,"temp_max":49.73,"pressure":1014,"sea_level":1014,"grnd_level":716,"humidity":83,"temp_kf":0},"weather":[{"id":500,"main":"Rain","description":"light rain","icon":"10d"}],"clouds":{"all":100},"wind":{"speed":1.79,"deg":205},"visibility":10000,"pop":0.61,"rain":{"3h":0.32},"sys":{"pod":"d"},"dt_txt":"2021-03-10 12:00:00"},{"dt":1615388400,"main":{"temp":57.51,"feels_like":54.91,"temp_min":57.51,"temp_max":57.51,"pressure":1016,"sea_level":1016,"grnd_level":720,"humidity":70,"temp_kf":0},"weather":[{"id":500,"main":"Rain","description":"light rain","icon":"10d"}],"clouds":{"all":96},"wind":{"speed":3.71,"deg":308},"visibility":10000,"pop":0.51,"rain":{"3h":0.5},"sys":{"pod":"d"},"dt_txt":"2021-03-10 15:00:00"},{"dt":1615399200,"main":{"temp":56.62,"feels_like":53.58,"temp_min":56.62,"temp_max":56.62,"pressure":1013,"sea_level":1013,"grnd_level":718,"humidity":78,"temp_kf":0},"weather":[{"id":500,"main":"Rain","description":"light rain","icon":"10d"}],"clouds":{"all":96},"wind":{"speed":5.48,"deg":292},"visibility":729,"pop":0.94,"rain":{"3h":2.44},"sys":{"pod":"d"},"dt_txt":"2021-03-10 18:00:00"},{"dt":1615410000,"main":{"temp":53.64,"feels_like":51.8,"temp_min":53.64,"temp_max":53.64,"pressure":1011,"sea_level":1011,"grnd_level":715,"humidity":83,"temp_kf":0},"weather":[{"id":500,"main":"Rain","description":"light rain","icon":"10d"}],"clouds":{"all":99},"wind":{"speed":2.75,"deg":306},"visibility":722,"pop":1,"rain":{"3h":2.86},"sys":{"pod":"d"},"dt_txt":"2021-03-10 21:00:00"},{"dt":1615420800,"main":{"temp":50.16,"feels_like":48.52,"temp_min":50.16,"temp_max":50.16,"pressure":1013,"sea_level":1013,"grnd_level":715,"humidity":87,"temp_kf":0},"weather":[{"id":501,"main":"Rain","description":"moderate rain","icon":"10n"}],"clouds":{"all":100},"wind":{"speed":1.43,"deg":104},"visibility":1055,"pop":1,"rain":{"3h":6.12},"sys":{"pod":"n"},"dt_txt":"2021-03-11 00:00:00"},{"dt":1615431600,"main":{"temp":48.38,"feels_like":45.23,"temp_min":48.38,"temp_max":48.38,"pressure":1016,"sea_level":1016,"grnd_level":716,"humidity":86,"temp_kf":0},"weather":[{"id":501,"main":"Rain","description":"moderate rain","icon":"10n"}],"clouds":{"all":100},"wind":{"speed":3.27,"deg":107},"visibility":3665,"pop":0.96,"rain":{"3h":9.83},"sys":{"pod":"n"},"dt_txt":"2021-03-11 03:00:00"},{"dt":1615442400,"main":{"temp":48.52,"feels_like":45.86,"temp_min":48.52,"temp_max":48.52,"pressure":1015,"sea_level":1015,"grnd_level":716,"humidity":84,"temp_kf":0},"weather":[{"id":501,"main":"Rain","description":"moderate rain","icon":"10n"}],"clouds":{"all":100},"wind":{"speed":2.21,"deg":136},"visibility":10000,"pop":0.96,"rain":{"3h":3.63},"sys":{"pod":"n"},"dt_txt":"2021-03-11 06:00:00"},{"dt":1615453200,"main":{"temp":48.36,"feels_like":46.76,"temp_min":48.36,"temp_max":48.36,"pressure":1014,"sea_level":1014,"grnd_level":715,"humidity":87,"temp_kf":0},"weather":[{"id":500,"main":"Rain","description":"light rain","icon":"10n"}],"clouds":{"all":100},"wind":{"speed":0.65,"deg":47},"visibility":10000,"pop":0.54,"rain":{"3h":0.98},"sys":{"pod":"n"},"dt_txt":"2021-03-11 09:00:00"},{"dt":1615464000,"main":{"temp":48.88,"feels_like":46.44,"temp_min":48.88,"temp_max":48.88,"pressure":1015,"sea_level":1015,"grnd_level":716,"humidity":85,"temp_kf":0},"weather":[{"id":500,"main":"Rain","description":"light rain","icon":"10d"}],"clouds":{"all":99},"wind":{"speed":2.1,"deg":105},"visibility":10000,"pop":0.39,"rain":{"3h":0.33},"sys":{"pod":"d"},"dt_txt":"2021-03-11 12:00:00"},{"dt":1615474800,"main":{"temp":59,"feels_like":56.26,"temp_min":59,"temp_max":59,"pressure":1015,"sea_level":1015,"grnd_level":721,"humidity":64,"temp_kf":0},"weather":[{"id":500,"main":"Rain","description":"light rain","icon":"10d"}],"clouds":{"all":100},"wind":{"speed":3.56,"deg":324},"visibility":10000,"pop":0.23,"rain":{"3h":0.25},"sys":{"pod":"d"},"dt_txt":"2021-03-11 15:00:00"},{"dt":1615485600,"main":{"temp":58.98,"feels_like":55.63,"temp_min":58.98,"temp_max":58.98,"pressure":1012,"sea_level":1012,"grnd_level":719,"humidity":70,"temp_kf":0},"weather":[{"id":500,"main":"Rain","description":"light rain","icon":"10d"}],"clouds":{"all":96},"wind":{"speed":5.7,"deg":311},"visibility":3827,"pop":1,"rain":{"3h":2.19},"sys":{"pod":"d"},"dt_txt":"2021-03-11 18:00:00"}],"city":{"id":3652462,"name":"San Fransisco","coord":{"lat":-0.3869,"lon":-78.5427},"country":"EC","population":1399814,"timezone":-18000,"sunrise":1615029721,"sunset":1615073340}}